MANIFEST.in
README.rst
VERSION
setup.py
pathquery/__init__.py
pathquery/exceptions.py
pathquery/query.py
pathquery.egg-info/PKG-INFO
pathquery.egg-info/SOURCES.txt
pathquery.egg-info/dependency_links.txt
pathquery.egg-info/not-zip-safe
pathquery.egg-info/requires.txt
pathquery.egg-info/top_level.txt